airflow_spell/__init__.py
airflow_spell/hooks/__init__.py
airflow_spell/hooks/spell_client.py
airflow_spell/operators/__init__.py
airflow_spell/operators/spell_run.py
airflow_spell-0.0.9.dist-info/LICENSE
airflow_spell-0.0.9.dist-info/METADATA
airflow_spell-0.0.9.dist-info/WHEEL
airflow_spell-0.0.9.dist-info/top_level.txt
airflow_spell-0.0.9.dist-info/RECORD
